CORDIC/cordic.v


//// CORDIC implementation in Verilog ////


`define K 32'h26dd3b6a  // Π(n=infinity) cos(alpha_n) --> 0.6072529350088814

module CORDIC #(
    parameter IN_WIDTH = 16,
    parameter EXTRA_BITS = 6
) (
    input clk,                          // Master Clock 
    // input rst,                       // Master asynchronous reset
    input  wire signed  [31:0] angle,   // phase_step 
    input  wire signed  [IN_WIDTH -1: 0]          x_init, y_init, 
    output wire signed  [(IN_WIDTH + EXTRA_BITS) -1: 0] cos, sin
    //output reg [31:0] phase_acc
);

    localparam WI = IN_WIDTH;
    localparam WXY = IN_WIDTH + EXTRA_BITS; // 22-bit data regs
    localparam STG = WXY;

    // arctan(2^-idx) = alpha_idx
    //reg [31:0] arctan_2n [0:30];
    wire [31:0] arctan_2n [0:30];

    // MSB 2'b00 (0,PI/2)
    // MSB 2'b01 (PI/2, PI)
    // MSB 2'b10 (PI, 3*PI/2)
    // MSB 2'b11 (3*PI/2, 2*PI)

    //                     32'b01000000000000000000000000000000  // upper 2 bits  = 2'b01 = 90 degree
    assign arctan_2n[00] = 32'b00100000000000000000000000000000; // alpha_0 = pi/4 rads
    assign arctan_2n[01] = 32'b00010010111001000000010100011101; // alpha_1 = 26.565 degrees
    assign arctan_2n[02] = 32'b00001001111110110011100001011011; // alpha_2 = 14.036 degrees
    assign arctan_2n[03] = 32'b00000101000100010001000111010100; 
    assign arctan_2n[04] = 32'b00000010100010110000110101000011;
    assign arctan_2n[05] = 32'b00000001010001011101011111100001;
    assign arctan_2n[06] = 32'b00000000101000101111011000011110;
    assign arctan_2n[07] = 32'b00000000010100010111110001010101;
    assign arctan_2n[08] = 32'b00000000001010001011111001010011;
    assign arctan_2n[09] = 32'b00000000000101000101111100101110;
    assign arctan_2n[10] = 32'b00000000000010100010111110011000;
    assign arctan_2n[11] = 32'b00000000000001010001011111001100;
    assign arctan_2n[12] = 32'b00000000000000101000101111100110;
    assign arctan_2n[13] = 32'b00000000000000010100010111110011;
    assign arctan_2n[14] = 32'b00000000000000001010001011111001;
    assign arctan_2n[15] = 32'b00000000000000000101000101111101;
    assign arctan_2n[16] = 32'b00000000000000000010100010111110;
    assign arctan_2n[17] = 32'b00000000000000000001010001011111;
    assign arctan_2n[18] = 32'b00000000000000000000101000101111;
    assign arctan_2n[19] = 32'b00000000000000000000010100011000;
    assign arctan_2n[20] = 32'b00000000000000000000001010001100;
    assign arctan_2n[21] = 32'b00000000000000000000000101000110;
    assign arctan_2n[22] = 32'b00000000000000000000000010100011;
    assign arctan_2n[23] = 32'b00000000000000000000000001010001;
    assign arctan_2n[24] = 32'b00000000000000000000000000101000;
    assign arctan_2n[25] = 32'b00000000000000000000000000010100;
    assign arctan_2n[26] = 32'b00000000000000000000000000001010;
    assign arctan_2n[27] = 32'b00000000000000000000000000000101;
    assign arctan_2n[28] = 32'b00000000000000000000000000000010;
    assign arctan_2n[29] = 32'b00000000000000000000000000000001; // arctan(2^-29)
    assign arctan_2n[30] = 32'b00000000000000000000000000000000;

    // initial begin
    //     $readmemb("arctan_table.txt", arctan_2n);
    //     $display("Arctan values loaded:");
        
    //     for (integer i = 0; i < 31; i = i + 1) begin
    //         $display("arctan_2n[%0d] = %b", i, arctan_2n[i]);
    //     end
    // end

    reg signed [WXY:0] _x [0:STG-1];
    reg signed [WXY:0] _y [0:STG-1];
    reg signed  [31:0] _z [0:STG-1];

    reg         [31:0] phase_acc; // phase accumulator

    wire [1:0] quadrant = phase_acc[31:30];
    wire signed [WI -1:0] NXin;
    wire signed [WI -1:0] NYin;

    assign NXin = -x_init;
    assign NYin = -y_init;
 
    always @(posedge clk) begin
        // make sure the rotation angle is in the -pi/2 to pi/2 range
        case(quadrant)
            2'b00,
            2'b11: begin // no changes needed for these quadrants
                _x[0] <= {x_init[WI -1], x_init} << (EXTRA_BITS -1);
                _y[0] <= {y_init[WI -1], y_init} << (EXTRA_BITS -1);
                _z[0] <= phase_acc;
            end
    
            2'b01: begin
                _x[0] <= {  NYin[WI -1], NYin}   << (EXTRA_BITS -1);
                _y[0] <= {x_init[WI -1], x_init} << (EXTRA_BITS -1);
                _z[0] <= {2'b00,phase_acc[29:0]}; // subtract pi/2 for angle in this quadrant
            end
    
            2'b10: begin
                _x[0] <= {y_init[WI -1], y_init} << (EXTRA_BITS -1);
                _y[0] <= {  NXin[WI -1], NXin}   << (EXTRA_BITS -1);
                _z[0] <= {2'b11,phase_acc[29:0]}; // add pi/2 to angles in this quadrant
            end
        endcase

        // advanced NCO
        phase_acc <= phase_acc + angle; // phase_step
    end

    genvar i;
    
    generate
    for (i=0; i< (STG -1); i = i+1) 
    
    begin: XYZ
        wire                   z_sgn;
        wire signed  [WXY -1 :0] x_shr, y_shr; 
    
        assign x_shr = _x[i] >>> i; // signed shift right
        assign y_shr = _y[i] >>> i;
    
        //the sign of the current rotation angle
        assign z_sgn = _z[i][31]; // z_sgn = 1 if _z[i] < 0
    
        always @(posedge clk) begin
           // add/subtract shifted data
           _x[i+1] <= z_sgn ? _x[i] + y_shr         : _x[i] - y_shr;
           _y[i+1] <= z_sgn ? _y[i] - x_shr         : _y[i] + x_shr;
           _z[i+1] <= z_sgn ? _z[i] + arctan_2n[i]  : _z[i] - arctan_2n[i];
        end
    end
    endgenerate

    assign sin = _y[IN_WIDTH -1];
    assign cos = _x[IN_WIDTH -1];

endmodule

CORDIC/cordic_tb.v
`timescale 1ns/100ps
`include "cordic.sv"

module cordic_testbench;

    reg  [15:0] Xin, Yin;
    reg  [31:0] frequency;
    wire [21:0] Xout, Yout, out_data_I, out_data_Q;
    wire  [31:0] phase_acc_out;
    reg         CLK_12MHz;

    initial begin 

        $dumpfile("./cordic.vcd");
        $dumpvars(0, cordic_testbench);

        CLK_12MHz = 1'b0;
        // Xin = 16'b0;
        // Yin = 16'd10000;
        Xin = 16'd10000;
        Yin = 16'b0;

        frequency = 32'h1555_5555; // 30 degrees at a time
        force orig.phase_acc = 0;
        #100;
        #5000;
        @(posedge CLK_12MHz);
        release orig.phase_acc;
        
        @(posedge CLK_12MHz); // 60
        @(posedge CLK_12MHz); // 90
        @(posedge CLK_12MHz); // 120
        @(posedge CLK_12MHz); // 150
        @(posedge CLK_12MHz); // 210
        @(posedge CLK_12MHz); // 240
        @(posedge CLK_12MHz); // 270
        @(posedge CLK_12MHz); // 300
        @(posedge CLK_12MHz); // 330
        @(posedge CLK_12MHz); // 360
        @(posedge CLK_12MHz); // 30

        force orig.phase_acc = 0;

        #20000 $finish;
    end

    CORDIC orig (CLK_12MHz, frequency, Xin, Yin, out_data_I, out_data_Q);

    parameter CLK12_SPEED = 40.7;

    always begin
            #CLK12_SPEED CLK_12MHz = 1'b1;
            #CLK12_SPEED CLK_12MHz = 1'b0;
    end

endmodule

CORDIC/cordic.vcd
$date
	Sun Oct 20 19:18:35 2024
$end
$version
	Icarus Verilog
$end
$timescale
	100ps
$end
$scope module cordic_testbench $end
$var wire 22 ! out_data_Q [21:0] $end
$var wire 22 " out_data_I [21:0] $end
$var reg 1 # CLK_12MHz $end
$var reg 16 $ Xin [15:0] $end
$var reg 16 % Yin [15:0] $end
$var reg 32 & frequency [31:0] $end
$scope module orig $end
$var wire 32 ' angle [31:0] $end
$var wire 1 # clk $end
$var wire 16 ( x_init [15:0] $end
$var wire 16 ) y_init [15:0] $end
$var wire 22 * sin [21:0] $end
$var wire 2 + quadrant [1:0] $end
$var wire 22 , cos [21:0] $end
$var wire 16 - NYin [15:0] $end
$var wire 16 . NXin [15:0] $end
$var reg 32 / phase_acc [31:0] $end
$scope begin XYZ[0] $end
$var wire 1 0 z_sgn $end
$var wire 22 1 y_shr [21:0] $end
$var wire 22 2 x_shr [21:0] $end
$upscope $end
$scope begin XYZ[1] $end
$var wire 1 3 z_sgn $end
$var wire 22 4 y_shr [21:0] $end
$var wire 22 5 x_shr [21:0] $end
$upscope $end
$scope begin XYZ[2] $end
$var wire 1 6 z_sgn $end
$var wire 22 7 y_shr [21:0] $end
$var wire 22 8 x_shr [21:0] $end
$upscope $end
$scope begin XYZ[3] $end
$var wire 1 9 z_sgn $end
$var wire 22 : y_shr [21:0] $end
$var wire 22 ; x_shr [21:0] $end
$upscope $end
$scope begin XYZ[4] $end
$var wire 1 < z_sgn $end
$var wire 22 = y_shr [21:0] $end
$var wire 22 > x_shr [21:0] $end
$upscope $end
$scope begin XYZ[5] $end
$var wire 1 ? z_sgn $end
$var wire 22 @ y_shr [21:0] $end
$var wire 22 A x_shr [21:0] $end
$upscope $end
$scope begin XYZ[6] $end
$var wire 1 B z_sgn $end
$var wire 22 C y_shr [21:0] $end
$var wire 22 D x_shr [21:0] $end
$upscope $end
$scope begin XYZ[7] $end
$var wire 1 E z_sgn $end
$var wire 22 F y_shr [21:0] $end
$var wire 22 G x_shr [21:0] $end
$upscope $end
$scope begin XYZ[8] $end
$var wire 1 H z_sgn $end
$var wire 22 I y_shr [21:0] $end
$var wire 22 J x_shr [21:0] $end
$upscope $end
$scope begin XYZ[9] $end
$var wire 1 K z_sgn $end
$var wire 22 L y_shr [21:0] $end
$var wire 22 M x_shr [21:0] $end
$upscope $end
$scope begin XYZ[10] $end
$var wire 1 N z_sgn $end
$var wire 22 O y_shr [21:0] $end
$var wire 22 P x_shr [21:0] $end
$upscope $end
$scope begin XYZ[11] $end
$var wire 1 Q z_sgn $end
$var wire 22 R y_shr [21:0] $end
$var wire 22 S x_shr [21:0] $end
$upscope $end
$scope begin XYZ[12] $end
$var wire 1 T z_sgn $end
$var wire 22 U y_shr [21:0] $end
$var wire 22 V x_shr [21:0] $end
$upscope $end
$scope begin XYZ[13] $end
$var wire 1 W z_sgn $end
$var wire 22 X y_shr [21:0] $end
$var wire 22 Y x_shr [21:0] $end
$upscope $end
$scope begin XYZ[14] $end
$var wire 1 Z z_sgn $end
$var wire 22 [ y_shr [21:0] $end
$var wire 22 \ x_shr [21:0] $end
$upscope $end
$scope begin XYZ[15] $end
$var wire 1 ] z_sgn $end
$var wire 22 ^ y_shr [21:0] $end
$var wire 22 _ x_shr [21:0] $end
$upscope $end
$scope begin XYZ[16] $end
$var wire 1 ` z_sgn $end
$var wire 22 a y_shr [21:0] $end
$var wire 22 b x_shr [21:0] $end
$upscope $end
$scope begin XYZ[17] $end
$var wire 1 c z_sgn $end
$var wire 22 d y_shr [21:0] $end
$var wire 22 e x_shr [21:0] $end
$upscope $end
$scope begin XYZ[18] $end
$var wire 1 f z_sgn $end
$var wire 22 g y_shr [21:0] $end
$var wire 22 h x_shr [21:0] $end
$upscope $end
$scope begin XYZ[19] $end
$var wire 1 i z_sgn $end
$var wire 22 j y_shr [21:0] $end
$var wire 22 k x_shr [21:0] $end
$upscope $end
$scope begin XYZ[20] $end
$var wire 1 l z_sgn $end
$var wire 22 m y_shr [21:0] $end
$var wire 22 n x_shr [21:0] $end
$upscope $end
$upscope $end
$upscope $end
$enddefinitions $end
#0
$dumpvars
bx n
bx m
xl
bx k
bx j
xi
bx h
bx g
xf
bx e
bx d
xc
bx b
bx a
x`
bx _
bx ^
x]
bx \
bx [
xZ
bx Y
bx X
xW
bx V
bx U
xT
bx S
bx R
xQ
bx P
bx O
xN
bx M
bx L
xK
bx J
bx I
xH
bx G
bx F
xE
bx D
bx C
xB
bx A
bx @
x?
bx >
bx =
x<
bx ;
bx :
x9
bx 8
bx 7
x6
bx 5
bx 4
x3
bx 2
bx 1
x0
b0 /
b1101100011110000 .
b0 -
bx ,
b0 +
bx *
b0 )
b10011100010000 (
b10101010101010101010101010101 '
b10101010101010101010101010101 &
b0 %
b10011100010000 $
0#
bx "
bx !
$end
#407
00
b0 1
b1001110001000000000 2
b0 /
1#
#814
0#
#1221
b100111000100000000 4
b100111000100000000 5
13
1#
#1628
0#
#2035
b1001110001000000 7
b11101010011000000 8
16
1#
#2442
0#
#2849
b1001110001000 :
b1111110111101000 ;
19
1#
#3256
0#
#3663
b1111111111100111100101 =
b1000000000101100 >
0<
1#
#4070
0#
#4477
b11110100 @
b100000001000111 A
1?
1#
#4884
0#
#5291
b1111111111111101111000 C
b10000000100111 D
0B
1#
#5698
0#
#6105
b1111111111111111111100 F
b1000000010100 G
0E
1#
#6512
0#
#6919
b1110 I
b100000001010 J
1H
1#
#7326
0#
#7733
b11 L
b10000000101 M
1K
1#
#8140
0#
#8547
b0 O
b1000000010 P
1N
1#
#8954
0#
#9361
b0 R
b100000001 S
1Q
1#
#9768
0#
#10175
b1111111111111111111111 U
b10000000 V
0T
1#
#10582
0#
#10989
b1111111111111111111111 X
b1000000 Y
0W
1#
#11396
0#
#11803
b0 [
b100000 \
1Z
1#
#12210
0#
#12617
b0 ^
b10000 _
1]
b110 !
b110 *
b10000000101001110110 "
b10000000101001110110 ,
1#
#13024
0#
#13431
b1111111111111111111111 a
b1000 b
0`
1#
#13838
0#
#14245
b1111111111111111111111 d
b100 e
0c
1#
#14652
0#
#15059
b0 g
b10 h
1f
1#
#15466
0#
#15873
b0 j
b1 k
1i
1#
#16280
0#
#16687
b1111111111111111111111 m
b0 n
0l
1#
